textpro/__init__.py
textpro/textpro.py
textpro-0.0.1.dist-info/LICENSE.txt
textpro-0.0.1.dist-info/METADATA
textpro-0.0.1.dist-info/WHEEL
textpro-0.0.1.dist-info/top_level.txt
textpro-0.0.1.dist-info/RECORD
